keepassxc/__init__.py
keepassxc/database.py
keepassxc_async-0.0.1.dist-info/LICENSE
keepassxc_async-0.0.1.dist-info/METADATA
keepassxc_async-0.0.1.dist-info/WHEEL
keepassxc_async-0.0.1.dist-info/top_level.txt
keepassxc_async-0.0.1.dist-info/RECORD
