Metadata-Version: 2.1
Name: keepassxc-async
Version: 0.0.1
Summary: Asyncio-compatible client for the KeePassXC browser protocol.
Author: Max Lang
Project-URL: Homepage, https://github.com/just-max/python-keepassxc-async
Project-URL: Repository, https://github.com/just-max/python-keepassxc-async.git
Project-URL: Issues, https://github.com/just-max/python-keepassxc-async/issues
Keywords: keepassxc,asyncio
Classifier: Development Status :: 3 - Alpha
Classifier: Intended Audience :: Developers
Classifier: License :: OSI Approved :: MIT License
Classifier: Programming Language :: Python :: 3
Classifier: Programming Language :: Python :: 3.12
Requires-Python: >=3.12
License-File: LICENSE
Requires-Dist: PyNaCl ~=1.5.0
